qtm_rt/__init__.py
qtm_rt/control.py
qtm_rt/discovery.py
qtm_rt/packet.py
qtm_rt/protocol.py
qtm_rt/qrt.py
qtm_rt/reboot.py
qtm_rt/receiver.py
qtm_rt/data/demo.qtm
qtm_rt-3.0.2.dist-info/LICENSE
qtm_rt-3.0.2.dist-info/METADATA
qtm_rt-3.0.2.dist-info/WHEEL
qtm_rt-3.0.2.dist-info/top_level.txt
qtm_rt-3.0.2.dist-info/zip-safe
qtm_rt-3.0.2.dist-info/RECORD
